bottle.py
bottle-0.12.22.data/scripts/bottle.py
bottle-0.12.22.dist-info/AUTHORS
bottle-0.12.22.dist-info/LICENSE
bottle-0.12.22.dist-info/METADATA
bottle-0.12.22.dist-info/WHEEL
bottle-0.12.22.dist-info/top_level.txt
bottle-0.12.22.dist-info/RECORD
