Metadata-Version: 2.1
Name: bottle
Version: 0.12.22
Summary: Fast and simple WSGI-framework for small web-applications.
Home-page: http://bottlepy.org/
Author: Marcel Hellkamp
Author-email: marc@gsites.de
License: MIT
Platform: any
Classifier: Development Status :: 4 - Beta
Classifier: Intended Audience :: Developers
Classifier: License :: OSI Approved :: MIT License
Classifier: Topic :: Internet :: WWW/HTTP :: Dynamic Content :: CGI Tools/Libraries
Classifier: Topic :: Internet :: WWW/HTTP :: HTTP Servers
Classifier: Topic :: Internet :: WWW/HTTP :: WSGI
Classifier: Topic :: Internet :: WWW/HTTP :: WSGI :: Application
Classifier: Topic :: Internet :: WWW/HTTP :: WSGI :: Middleware
Classifier: Topic :: Internet :: WWW/HTTP :: WSGI :: Server
Classifier: Topic :: Software Development :: Libraries :: Application Frameworks
Classifier: Programming Language :: Python :: 2.5
Classifier: Programming Language :: Python :: 2.6
Classifier: Programming Language :: Python :: 2.7
Classifier: Programming Language :: Python :: 3
Classifier: Programming Language :: Python :: 3.2
Classifier: Programming Language :: Python :: 3.3
Classifier: Programming Language :: Python :: 3.4
Classifier: Programming Language :: Python :: 3.5
Classifier: Programming Language :: Python :: 3.6
Classifier: Programming Language :: Python :: 3.7
License-File: LICENSE
License-File: AUTHORS
